text_outputter/__init__.py
text_outputter/cli.py
text_outputter-0.3.0.dist-info/METADATA
text_outputter-0.3.0.dist-info/WHEEL
text_outputter-0.3.0.dist-info/entry_points.txt
text_outputter-0.3.0.dist-info/top_level.txt
text_outputter-0.3.0.dist-info/RECORD
